Workbook

Sheet raw data
A2: TATA MOTORS FINANCIAL DATA
A3: FINANCIAL YEARS : FY2021 TO 2025
A4: SOURCE : ANNUAL REPORT /COMPANY FINANCIAL STATEMENT
A6: Particulars | B6: FY2021 | C6: FY2022 | D6: FY2023 | E6: FY2024 | F6: FY2025
A7: REVENUE | B7: 249795 | C7: 278454 | D7: 345967 | E7: 434016 | F7: 439695
A8: EBITDA | B8: 30397 | C8: 26721 | D8: 34796 | E8: 62800 | F8: 57600
A9: EBIT | B9: 6471 | C9: 1949 | D9: 17304 | E9: 36000 | F9: 34700
A10: PROFIT AFTER TAX (PAT) | B10: -13395.1 | C10: -11411 | D10: 2690 | E10: 31807 | F10: 28149
A11: TOTAL ASSETS | B11: 343125.8 | C11: 330620 | D11: 365725 | E11: 370664 | F11: 378642
A12: TOTAL DEBT | B12: 135905 | C12: 139677 | D12: 130354 | E12: 109937 | F12: 62499
A13: SHAREHOLDERS' EQUITY | B13: 56820 | C13: 44832 | D13: 68273 | E13: 93094 | F13: 122754
A14: EPS | B14: -39.06 | C14: -4.54 | D14: 6.29 | E14: 81.95 | F14: 78.8

Sheet calculations
A1: TATA MOTORS - FINANCIAL CALCULATIONS
A2: CONSOLIDATED FINANCIAL ANALSIS| FY2021-2025
A3: particulars | B3: FY2021 | C3: FY2022 | D3: FY2023 | E3: FY2024 | F3: FY2025
A4: revenue growth % | B4: N/A | C4: ='raw data'!C7/'raw data'!B7-1 -> 0.11473008 | D4: ='raw data'!D7/'raw data'!C7-1 -> 0.24245656 | E4: ='raw data'!E7/'raw data'!D7-1 -> 0.25450115 | F4: ='raw data'!F7/'raw data'!E7-1 -> 0.013084771
A5: EBITDA MARGIN % | B5: ='raw data'!B8/'raw data'!B7 -> 0.12168778 | C5: ='raw data'!C8/'raw data'!C7 -> 0.09596199 | D5: ='raw data'!D8/'raw data'!D7 -> 0.10057607 | E5: ='raw data'!E8/'raw data'!E7 -> 0.14469513 | F5: ='raw data'!F8/'raw data'!F7 -> 0.1309999
A6: EBIT MARGIN % | B6: ='raw data'!B9/'raw data'!B7 -> 0.025905242 | C6: ='raw data'!C9/'raw data'!C7 -> 0.0069993608 | D6: ='raw data'!D9/'raw data'!D7 -> 0.050016331 | E6: ='raw data'!E9/'raw data'!E7 -> 0.082946251 | F6: ='raw data'!F9/'raw data'!F7 -> 0.078918341
A7: PAT MARGINS % | B7: ='raw data'!B10/'raw data'!$B7 -> -0.053624372 | C7: ='raw data'!C10/'raw data'!$C7 -> -0.040979839 | D7: ='raw data'!D10/'raw data'!$D7 -> 0.007775308 | E7: ='raw data'!E10/'raw data'!$E7 -> 0.073285317 | F7: ='raw data'!F10/'raw data'!$F7 -> 0.064019377
A8: RETURN ON ASSET | B8: ='raw data'!B10/'raw data'!B11 -> -0.039038452 | C8: ='raw data'!C10/'raw data'!C11 -> -0.034513944 | D8: ='raw data'!D10/'raw data'!D11 -> 0.0073552533 | E8: ='raw data'!E10/'raw data'!E11 -> 0.085810869 | F8: ='raw data'!F10/'raw data'!F11 -> 0.074341991
A9: RETURN ON EQUITY | B9: ='raw data'!B10/'raw data'!B13 -> -0.23574622 | C9: ='raw data'!C10/'raw data'!C13 -> -0.25452802 | D9: ='raw data'!D10/'raw data'!D13 -> 0.039400642 | E9: ='raw data'!E10/'raw data'!E13 -> 0.34166541 | F9: ='raw data'!F10/'raw data'!F13 -> 0.22931228
A10: DEBT TO EQUITY | B10: ='raw data'!B12/'raw data'!B13 -> 2.3918515 | C10: ='raw data'!C12/'raw data'!C13 -> 3.1155648 | D10: ='raw data'!D12/'raw data'!D13 -> 1.9093053 | E10: ='raw data'!E12/'raw data'!E13 -> 1.1809247 | F10: ='raw data'!F12/'raw data'!F13 -> 0.50914023
A11: EPS GROWTH | B11: N/A | C11: =('raw data'!C14-'raw data'!B14)-1 -> 33.52 | D11: =('raw data'!D14-'raw data'!C14)-1 -> 9.83 | E11: =('raw data'!E14-'raw data'!D14)-1 -> 74.66 | F11: =('raw data'!F14-'raw data'!E14)-1 -> -4.15
A12: DEBT TO EBITDA | B12: ='raw data'!$B12/'raw data'!B8 -> 4.4710004 | C12: ='raw data'!$C12/'raw data'!C8 -> 5.227237 | D12: ='raw data'!$D12/'raw data'!D8 -> 3.7462352 | E12: ='raw data'!$E12/'raw data'!E8 -> 1.7505892 | F12: ='raw data'!$F12/'raw data'!F8 -> 1.0850521

Sheet CHARTS
C1: TATA MOTORS - FINACIAL CHARTS

Sheet dashboard
A2: Tata Motors - Financial Performance Dashboard
B4: consolidated Financial analysis| fy2021-fy2025
B5: YEAR | C5: FY2025
B6: REVENUE | C6: FY25 | D6: NET PROFIT(FY25 | E6: FY25 | F6: EBITDA MARGIN% FY25 | H6: ROE % FY25 | J6: DEBT EQUITY FY25 | L6: EPS FY25
B7: =INDEX('raw data'!$B$7:$F$14,MATCH(dashboard!$B$6,'raw data'!$A$7:$A$14,0),MATCH(dashboard!$C$5,'raw data'!$B$6:$F$6,0)) -> #N/A | D7: ='raw data'!F10 -> 28149 | F7: =calculations!F5 -> 0.1309999 | H7: =calculations!F9 -> 0.22931228 | J7: =calculations!F10 -> 0.50914023 | L7: ='raw data'!F14 -> 78.8
B8: =INDEX('raw data'!$B$7:$F$7,1,MATCH(dashboard!$C$5,'raw data'!$B$6:$F$6,0)) -> #N/A
B42: KEY INSIGHTS:
B44: Revenue grew from Rs.2.49L Cr(FY21) to Rs. 4.39L Cr (FY25)
B45: Company turned from loss to profit , PAT margin improved to X%
B46: Debt - equity improved, showing stronger solvency
